{
  "num_processes": 14,
  "processes": [
    {
      "pid": 12,
      "arrival_time": 2,
      "burst_time": 41,
      "priority": 3
    },
    {
      "pid": 0,
      "arrival_time": 6,
      "burst_time": 4,
      "priority": 5
    },
    {
      "pid": 9,
      "arrival_time": 10,
      "burst_time": 21,
      "priority": 7
    },
    {
      "pid": 4,
      "arrival_time": 15,
      "burst_time": 11,
      "priority": 6
    },
    {
      "pid": 3,
      "arrival_time": 20,
      "burst_time": 5,
      "priority": 6
    },
    {
      "pid": 5,
      "arrival_time": 21,
      "burst_time": 7,
      "priority": 1
    },
    {
      "pid": 10,
      "arrival_time": 24,
      "burst_time": 17,
      "priority": 5
    },
    {
      "pid": 2,
      "arrival_time": 28,
      "burst_time": 21,
      "priority": 5
    },
    {
      "pid": 6,
      "arrival_time": 28,
      "burst_time": 15,
      "priority": 5
    },
    {
      "pid": 13,
      "arrival_time": 40,
      "burst_time": 1,
      "priority": 6
    },
    {
      "pid": 11,
      "arrival_time": 69,
      "burst_time": 13,
      "priority": 1
    },
    {
      "pid": 8,
      "arrival_time": 72,
      "burst_time": 10,
      "priority": 6
    },
    {
      "pid": 1,
      "arrival_time": 83,
      "burst_time": 10,
      "priority": 2
    },
    {
      "pid": 7,
      "arrival_time": 88,
      "burst_time": 10,
      "priority": 4
    }
  ],
  "time_quantum": 1,
  "stats": {
    "avg_burst": 13.285714285714286,
    "arrival_std": 29.403969231949052,
    "burst_skew": 1.5133104133724624
  }
}