{
  "num_processes": 7,
  "processes": [
    {
      "pid": 4,
      "arrival_time": 18,
      "burst_time": 4,
      "priority": 4
    },
    {
      "pid": 5,
      "arrival_time": 18,
      "burst_time": 30,
      "priority": 6
    },
    {
      "pid": 6,
      "arrival_time": 18,
      "burst_time": 10,
      "priority": 3
    },
    {
      "pid": 0,
      "arrival_time": 60,
      "burst_time": 9,
      "priority": 5
    },
    {
      "pid": 2,
      "arrival_time": 84,
      "burst_time": 21,
      "priority": 3
    },
    {
      "pid": 3,
      "arrival_time": 91,
      "burst_time": 28,
      "priority": 4
    },
    {
      "pid": 1,
      "arrival_time": 92,
      "burst_time": 7,
      "priority": 4
    }
  ],
  "time_quantum": 9,
  "stats": {
    "avg_burst": 15.571428571428571,
    "arrival_std": 35.67378656126999,
    "burst_skew": 0.3703423259680695
  }
}